Default_Configs/default_auto.json
Default_Configs/default_auto.toml
Default_Configs/default_auto.xml
Default_Configs/default_auto.yaml
Default_Configs/default_manual.json
Default_Configs/default_manual.toml
Default_Configs/default_manual.xml
Default_Configs/default_manual.yaml
PKIPractice/RunConfig.py
PKIPractice/__init__.py
PKIPractice/Simulation/Certificate.py
PKIPractice/Simulation/DBUtils.py
PKIPractice/Simulation/Holder.py
PKIPractice/Simulation/Network.py
PKIPractice/Simulation/SimUtils.py
PKIPractice/Simulation/SocketUtils.py
PKIPractice/Simulation/__init__.py
PKIPractice/Utilities/CLIUtils.py
PKIPractice/Utilities/DataclassUtils.py
PKIPractice/Utilities/EnumUtils.py
PKIPractice/Utilities/IngestUtils.py
PKIPractice/Utilities/__init__.py
PKIPractice/tests/__init__.py
PKIPractice/tests/test_cli.py
PKIPractice/tests/test_enums.py
PKIPractice/tests/test_holder.py
PKIPractice/tests/test_ingestion.py
PKIPractice/tests/test_network.py
pypkipractice-2.4.3.dist-info/licenses/LICENSE
pypkipractice-2.4.3.dist-info/METADATA
pypkipractice-2.4.3.dist-info/WHEEL
pypkipractice-2.4.3.dist-info/entry_points.txt
pypkipractice-2.4.3.dist-info/top_level.txt
pypkipractice-2.4.3.dist-info/RECORD
