Metadata-Version: 2.4
Name: PyPkiPractice
Version: 2.4.3
Summary: A project that, given two input files, can simulate the usage of a Public-Key Infrastructure while devices communicate
Author-email: Laolu Adewoye <laoluadewoye@gmail.com>
License: MIT License
Project-URL: Repository, https://github.com/laoluadewoye/PKI_Practice_Python
Project-URL: DockerHub, https://hub.docker.com/r/laoluade/pypkipractice
Keywords: Digital Certificates,Public-Key Infrastructure,PKI,Certificate Authorities,Digital Signatures,Encryption,Cryptography,Python,Simulation
Classifier: Development Status :: 3 - Alpha
Classifier: Environment :: Console
Classifier: Environment :: Web Environment
Classifier: Framework :: Flask
Classifier: Intended Audience :: Education
Classifier: Intended Audience :: End Users/Desktop
Classifier: Intended Audience :: Information Technology
Classifier: Intended Audience :: Other Audience
Classifier: Intended Audience :: Science/Research
Classifier: License :: OSI Approved :: MIT License
Classifier: Natural Language :: English
Classifier: Operating System :: OS Independent
Classifier: Programming Language :: JavaScript
Classifier: Programming Language :: Python :: 3
Classifier: Programming Language :: Python :: 3.9
Classifier: Programming Language :: Python :: 3.10
Classifier: Programming Language :: Python :: 3.11
Classifier: Programming Language :: Python :: 3.12
Classifier: Programming Language :: Python :: 3.13
Classifier: Programming Language :: Python :: 3.14
Classifier: Programming Language :: SQL
Classifier: Topic :: Communications
Classifier: Topic :: Internet :: WWW/HTTP
Classifier: Topic :: Scientific/Engineering
Requires-Python: <=3.14,>=3.9
License-File: LICENSE
Requires-Dist: PyYAML==6.0.2
Requires-Dist: tomli==2.2.1
Requires-Dist: cryptography==44.0.1
Requires-Dist: Flask==3.0.3
Requires-Dist: waitress==3.0.2
Requires-Dist: asciidoc==10.2.1
Dynamic: license-file
